{
  "teacher": {
    "baseScale": 0.95,
    "outlineKey": "ca_sau_outline",
    "baseX_pct": 0.45,
    "baseY_pct": 0.65,
    "parts": [
      { "key": "ca_sau_1", "offsetX": 0, "offsetY": 0, "scale": 0.95, "hintPoints": [{"x": 0, "y": 0}]}
    ]
  },
  "letter": {
    "baseScale": 0.6,
    "outlineKey": "ca_sau_template",
    "frameKey": "ca_sau_frame",
    "baseX_pct": 0.13,
    "baseY_pct": 0.25,
    "parts": []
  },
  "name": {
    "baseScale": 0.6,
    "outlineKey": "ca_sau_name",
    "frameKey": "ca_sau_name_bg",
    "baseX_pct": 0.12,
    "baseY_pct": 0.38,
    "parts": []
  }
}